explicit_numpy_broadcast/__init__.py
explicit_numpy_broadcast/aaexplicit_numpy_broadcast.py
explicit_numpy_broadcast/explicit_numpy_broadcast.py
explicit_numpy_broadcast-1.0.3.dist-info/LICENSE
explicit_numpy_broadcast-1.0.3.dist-info/METADATA
explicit_numpy_broadcast-1.0.3.dist-info/WHEEL
explicit_numpy_broadcast-1.0.3.dist-info/top_level.txt
explicit_numpy_broadcast-1.0.3.dist-info/RECORD
