Metadata-Version: 2.1
Name: explicit-numpy-broadcast
Version: 1.0.3
Summary: Explicit broadcasting rules in Jupyter for numpy arrays
Home-page: https://github.com/bellecp/explicit_numpy_broadcast
Author: bellecp
Author-email: pierre.bellec@rutgers.edu
License: UNKNOWN
Platform: UNKNOWN
Classifier: Programming Language :: Python :: 3
Classifier: License :: OSI Approved :: MIT License
Classifier: Operating System :: OS Independent
License-File: LICENSE
